conseil/__init__.py
conseil/api.py
conseil/core.py
conseil/docstring.py
conseil/query.py
conseil-0.1.4.dist-info/LICENSE
conseil-0.1.4.dist-info/WHEEL
conseil-0.1.4.dist-info/METADATA
conseil-0.1.4.dist-info/RECORD
