Metadata-Version: 2.1
Name: conseil
Version: 0.1.4
Summary: Python toolkit for Conseil blockchain indexer
Home-page: https://github.com/baking-bad/conseilpy
License: MIT
Keywords: tezos,blockchain
Author: Michael Zaikin
Author-email: mz@baking-bad.org
Requires-Python: >=3.6,<4.0
Classifier: License :: OSI Approved :: MIT License
Classifier: Operating System :: OS Independent
Classifier: Programming Language :: Python :: 3
Classifier: Programming Language :: Python :: 3.6
Classifier: Programming Language :: Python :: 3.7
Requires-Dist: requests
Project-URL: Repository, https://github.com/baking-bad/conseilpy
